[{"id":0,"athleteId":0,"date":"2021-05-12T15:46:55.408Z","action":"stop"},{"id":null,"athleteId":0,"date":"2021-05-12T15:47:03.132Z","action":"stop"},{"id":1,"athleteId":0,"date":"2021-05-12T15:47:32.003Z","action":"stop"},{"id":2,"athleteId":0,"date":"2021-05-12T15:47:48.725Z","action":"stop"},{"id":3,"athleteId":0,"date":"2021-05-12T15:48:13.456Z","action":"stop"},{"id":4,"athleteId":0,"date":"2021-05-12T15:48:14.214Z","action":"stop"},{"id":5,"athleteId":0,"date":"2021-05-12T15:51:34.649Z","action":"stop"},{"id":6,"athleteId":0,"date":"2021-05-12T16:08:19.524Z","action":"start"},{"id":7,"athleteId":0,"date":"2021-05-12T16:15:06.781Z","action":"stop"},{"id":8,"athleteId":0,"date":"2021-05-12T16:18:09.923Z","action":"start"},{"id":9,"athleteId":-1,"date":"2021-05-14T08:29:27.292Z"},{"id":10,"athleteId":3,"date":"2021-05-14T08:29:37.022Z","action":"start"},{"id":11,"athleteId":3,"date":"2021-05-14T08:35:08.424Z"},{"id":12,"athleteId":3,"date":"2021-05-14T08:35:44.367Z","action":"start"},{"id":13,"athleteId":3,"date":"2021-05-17T13:19:11.958Z","action":"stop"},{"id":14,"athleteId":3,"date":"2021-05-17T14:03:20.210Z","action":"stop"},{"id":15,"athleteId":2,"date":"2021-05-18T09:59:50.478Z","action":"pause"},{"id":16,"athleteId":2,"date":"2021-05-18T10:33:21.288Z","action":"start"},{"id":17,"athleteId":2,"date":"2021-05-18T10:33:42.568Z","action":"stop"},{"id":18,"athleteId":-1,"date":"2021-05-24T12:26:41.284Z","action":"start"},{"id":19,"athleteId":-1,"date":"2021-05-24T12:27:57.655Z","action":"start"},{"id":20,"athleteId":-1,"date":"2021-05-24T12:29:19.162Z","action":"start"},{"id":21,"athleteId":0,"date":"2021-05-24T12:30:08.232Z","action":"start"},{"id":22,"athleteId":4,"date":"2021-05-24T12:30:31.440Z","action":"start"},{"id":23,"athleteId":4,"date":"2021-05-26T21:04:57.256Z","action":"start"},{"id":24,"athleteId":4,"date":"2021-05-26T21:05:01.419Z","action":"stop"},{"id":25,"athleteId":4,"date":"2021-05-26T21:06:57.096Z","action":"start"},{"id":26,"athleteId":4,"date":"2021-05-26T21:11:41.047Z","action":"start"},{"id":27,"athleteId":4,"date":"2021-05-26T21:14:38.624Z","action":"stop"},{"id":28,"athleteId":4,"date":"2021-05-26T21:16:07.889Z","action":"start"},{"id":29,"athleteId":4,"date":"2021-05-26T21:20:22.092Z","action":"stop"},{"id":30,"athleteId":4,"date":"2021-05-26T21:21:11.871Z","action":"start"},{"id":31,"athleteId":4,"date":"2021-05-26T21:27:37.332Z","action":"stop"},{"id":32,"athleteId":7,"date":"2021-05-26T21:28:06.931Z","action":"start"},{"id":33,"athleteId":7,"date":"2021-05-26T21:28:22.121Z","action":"stop"},{"id":34,"athleteId":7,"date":"2021-05-26T21:30:10.303Z","action":"start"},{"id":35,"athleteId":7,"date":"2021-05-26T21:30:22.100Z","action":"stop"},{"id":36,"athleteId":7,"date":"2021-05-26T21:32:06.176Z","action":"start"},{"id":37,"athleteId":7,"date":"2021-05-26T21:33:24.225Z","action":"stop"},{"id":38,"athleteId":7,"date":"2021-05-26T21:42:34.324Z","action":"start"},{"id":39,"athleteId":7,"date":"2021-05-26T21:44:23.972Z","action":"stop"},{"id":40,"athleteId":7,"date":"2021-05-26T21:44:32.403Z","action":"start"},{"id":41,"athleteId":7,"date":"2021-05-26T21:45:06.311Z","action":"stop"},{"id":42,"athleteId":7,"date":"2021-05-26T21:46:00.956Z","action":"start"},{"id":43,"athleteId":7,"date":"2021-05-26T21:47:27.840Z","action":"stop"},{"id":44,"athleteId":7,"date":"2021-05-26T21:48:17.169Z","action":"start"},{"id":45,"athleteId":7,"date":"2021-05-26T21:48:31.329Z","action":"stop"},{"id":46,"athleteId":7,"date":"2021-05-26T21:51:27.715Z","action":"start"},{"id":47,"athleteId":7,"date":"2021-06-20T13:59:43.932Z","action":"stop"},{"id":48,"athleteId":0,"date":"2021-06-20T14:05:21.954Z","action":"start"},{"id":49,"athleteId":0,"date":"2021-06-20T14:05:44.256Z","action":"stop"},{"id":50,"athleteId":0,"date":"2021-06-20T14:05:58.801Z","action":"start"},{"id":51,"athleteId":0,"date":"2021-06-20T14:07:21.038Z","action":"stop"},{"id":52,"athleteId":0,"date":"2021-06-20T14:07:29.997Z","action":"start"},{"id":53,"athleteId":0,"date":"2021-06-20T14:08:30.593Z","action":"stop"},{"id":54,"athleteId":0,"date":"2021-06-20T14:08:46.984Z","action":"start"},{"id":55,"athleteId":0,"date":"2021-06-20T14:09:01.015Z","action":"stop"},{"id":56,"athleteId":0,"date":"2021-06-20T14:11:42.020Z","action":"start"},{"id":57,"athleteId":0,"date":"2021-06-20T14:12:02.762Z","action":"stop"},{"id":58,"athleteId":0,"date":"2021-06-20T14:12:14.300Z","action":"start"},{"id":59,"athleteId":0,"date":"2021-06-20T14:12:28.251Z","action":"stop"},{"id":60,"athleteId":0,"date":"2021-06-20T14:12:35.475Z","action":"start"},{"id":61,"athleteId":0,"date":"2021-06-20T14:12:48.612Z","action":"stop"},{"id":62,"athleteId":0,"date":"2021-06-20T14:13:15.044Z","action":"start"},{"id":63,"athleteId":0,"date":"2021-06-20T14:14:16.137Z","action":"stop"},{"id":64,"athleteId":0,"date":"2021-06-20T14:17:10.470Z","action":"start"},{"id":65,"athleteId":0,"date":"2021-06-20T14:18:11.471Z","action":"stop"},{"id":66,"athleteId":0,"date":"2021-06-20T14:43:54.298Z","action":"start"},{"id":67,"athleteId":0,"date":"2021-06-20T14:44:55.346Z","action":"stop"},{"id":68,"athleteId":0,"date":"2021-06-20T14:45:52.560Z","action":"start"},{"id":69,"athleteId":0,"date":"2021-06-20T14:54:40.586Z","action":"stop"},{"id":70,"athleteId":0,"date":"2021-06-20T14:55:54.786Z","action":"start"},{"id":71,"athleteId":0,"date":"2021-06-20T15:04:48.002Z","action":"stop"},{"id":72,"athleteId":0,"date":"2021-06-20T15:20:47.587Z","action":"start"},{"id":73,"athleteId":0,"date":"2021-06-20T15:20:56.560Z","action":"stop"},{"id":74,"athleteId":0,"date":"2021-06-20T15:22:15.006Z","action":"start"},{"id":75,"athleteId":0,"date":"2021-06-20T15:22:28.760Z","action":"stop"},{"id":76,"athleteId":0,"date":"2021-06-20T15:22:47.884Z","action":"start"},{"id":77,"athleteId":0,"date":"2021-06-20T15:22:51.880Z","action":"stop"},{"id":78,"athleteId":0,"date":"2021-06-20T15:27:16.208Z","action":"start"},{"id":79,"athleteId":0,"date":"2021-06-20T15:27:48.238Z","action":"stop"},{"id":80,"athleteId":0,"date":"2021-06-20T15:29:18.720Z","action":"start"},{"id":81,"athleteId":0,"date":"2021-06-20T15:29:23.562Z","action":"stop"},{"id":82,"athleteId":0,"date":"2021-06-20T15:29:31.017Z","action":"start"},{"id":83,"athleteId":0,"date":"2021-06-20T15:30:31.251Z","action":"stop"},{"id":84,"athleteId":0,"date":"2021-06-20T15:37:02.855Z","action":"start"},{"id":85,"athleteId":0,"date":"2021-06-20T15:37:24.079Z","action":"stop"},{"id":86,"athleteId":0,"date":"2021-06-20T15:40:30.259Z","action":"start"},{"id":87,"athleteId":0,"date":"2021-06-20T15:40:42.683Z","action":"stop"},{"id":88,"athleteId":0,"date":"2021-06-20T15:40:53.478Z","action":"start"},{"id":89,"athleteId":0,"date":"2021-06-20T15:41:13.916Z","action":"stop"},{"id":90,"athleteId":0,"date":"2021-06-20T15:41:19.139Z","action":"start"},{"id":91,"athleteId":0,"date":"2021-06-20T15:41:49.454Z","action":"stop"},{"id":92,"athleteId":0,"date":"2021-06-20T15:45:17.241Z","action":"start"},{"id":93,"athleteId":0,"date":"2021-06-20T15:45:30.118Z","action":"stop"},{"id":94,"athleteId":0,"art":"liegend","date":"2021-06-20T15:49:18.227Z","action":"start"},{"id":95,"athleteId":0,"date":"2021-06-20T15:49:42.104Z","action":"stop"},{"id":96,"athleteId":0,"art":"liegend","date":"2021-06-20T15:52:10.759Z","action":"start"},{"id":97,"athleteId":0,"date":"2021-06-20T15:52:22.782Z","action":"stop"},{"id":98,"athleteId":0,"art":"liegend","date":"2021-06-20T15:52:32.430Z","action":"start"},{"id":99,"athleteId":0,"date":"2021-06-20T15:52:43.474Z","action":"stop"},{"id":100,"athleteId":0,"art":"liegend","date":"2021-06-20T16:07:13.921Z","action":"start"},{"id":101,"athleteId":0,"date":"2021-06-20T16:07:26.264Z","action":"stop"},{"id":102,"athleteId":0,"art":"liegend","date":"2021-06-20T16:08:04.880Z","action":"start"},{"id":103,"athleteId":0,"date":"2021-06-20T16:08:16.033Z","action":"stop"},{"id":104,"athleteId":0,"art":"liegend","date":"2021-06-20T16:08:43.109Z","action":"start"},{"id":105,"athleteId":0,"date":"2021-06-20T16:09:32.096Z","action":"stop"},{"id":106,"athleteId":0,"art":"liegend","date":"2021-06-20T16:12:07.436Z","action":"start"},{"id":107,"athleteId":0,"date":"2021-06-20T16:12:34.574Z","action":"stop"},{"id":108,"athleteId":0,"art":"liegend","date":"2021-06-20T16:13:26.083Z","action":"start"},{"id":109,"athleteId":0,"date":"2021-06-20T16:13:48.095Z","action":"stop"},{"id":110,"athleteId":0,"art":"liegend","date":"2021-06-20T16:22:39.945Z","action":"start"},{"id":111,"athleteId":0,"date":"2021-06-20T16:23:08.431Z","action":"stop"},{"id":112,"athleteId":0,"art":"liegend","date":"2021-06-20T16:23:17.705Z","action":"start"},{"id":113,"athleteId":0,"date":"2021-06-20T16:24:18.375Z","action":"stop"},{"id":114,"athleteId":0,"art":"liegend","date":"2021-06-20T16:24:23.354Z","action":"start"},{"id":115,"athleteId":0,"date":"2021-06-20T16:25:24.414Z","action":"stop"},{"id":116,"athleteId":0,"art":"liegend","date":"2021-06-20T16:27:58.823Z","action":"start"},{"id":117,"athleteId":0,"date":"2021-06-20T16:28:22.898Z","action":"stop"},{"id":118,"athleteId":0,"art":"liegend","date":"2021-06-20T16:29:00.429Z","action":"start"},{"id":119,"athleteId":0,"art":"liegend","date":"2021-06-20T16:29:09.657Z","action":"start"},{"id":120,"athleteId":0,"art":"liegend","date":"2021-06-20T16:29:33.612Z","action":"start"},{"id":121,"athleteId":0,"date":"2021-06-20T16:29:37.644Z","action":"stop"},{"id":122,"athleteId":0,"art":"liegend","date":"2021-06-20T16:29:43.238Z","action":"start"},{"id":123,"athleteId":0,"date":"2021-06-20T16:30:01.027Z","action":"stop"},{"id":124,"athleteId":0,"art":"liegend","date":"2021-06-20T16:30:04.743Z","action":"start"},{"id":125,"athleteId":0,"art":"liegend","date":"2021-06-20T16:33:00.590Z","action":"start"},{"id":126,"athleteId":0,"date":"2021-06-20T16:33:14.486Z","action":"stop"},{"id":127,"athleteId":0,"art":"liegend","date":"2021-06-20T16:33:23.603Z","action":"start"},{"id":128,"athleteId":0,"date":"2021-06-27T14:47:06.580Z","action":"stop"},{"id":129,"athleteId":0,"date":"2021-06-27T14:58:20.221Z","action":"stop"},{"id":130,"athleteId":0,"art":"liegend","date":"2021-06-27T14:58:28.605Z","action":"start"},{"id":131,"athleteId":0,"date":"2021-06-27T14:58:57.827Z","action":"stop"},{"id":132,"athleteId":0,"art":"liegend","date":"2021-06-27T14:59:11.616Z","action":"start"},{"id":133,"athleteId":0,"date":"2021-06-27T14:59:32.562Z","action":"stop"},{"id":134,"athleteId":0,"art":"liegend","date":"2021-06-27T15:00:18.408Z","action":"start"},{"id":135,"athleteId":0,"date":"2021-06-27T15:00:32.570Z","action":"stop"},{"id":136,"athleteId":0,"art":"liegend","date":"2021-06-27T15:05:48.939Z","action":"start"},{"id":137,"athleteId":0,"art":"liegend","date":"2021-06-27T15:06:43.921Z","action":"start"},{"id":138,"athleteId":0,"date":"2021-06-27T15:06:58.862Z","action":"stop"},{"id":139,"athleteId":0,"art":"liegend","date":"2021-06-27T15:07:19.549Z","action":"start"},{"id":140,"athleteId":0,"date":"2021-06-27T15:07:39.941Z","action":"stop"},{"id":141,"athleteId":0,"art":"liegend","date":"2021-06-27T15:07:50.269Z","action":"start"},{"id":142,"athleteId":0,"date":"2021-06-27T15:08:37.397Z","action":"stop"},{"id":143,"athleteId":0,"art":"liegend","date":"2021-06-27T15:08:44.029Z","action":"start"},{"id":144,"athleteId":0,"date":"2021-06-27T15:08:57.582Z","action":"stop"},{"id":145,"athleteId":0,"art":"liegend","date":"2021-06-27T15:09:10.757Z","action":"start"},{"id":146,"athleteId":0,"date":"2021-06-27T15:10:24.536Z","action":"stop"},{"id":147,"athleteId":0,"art":"liegend","date":"2021-06-27T15:10:30.305Z","action":"start"},{"id":148,"athleteId":0,"date":"2021-06-27T15:10:45.652Z","action":"stop"},{"id":149,"athleteId":0,"art":"liegend","date":"2021-06-27T15:11:13.129Z","action":"start"},{"id":150,"athleteId":0,"date":"2021-06-27T15:11:29.554Z","action":"stop"},{"id":151,"athleteId":0,"art":"liegend","date":"2021-06-27T15:11:55.480Z","action":"start"},{"id":152,"athleteId":0,"date":"2021-06-27T15:12:05.161Z","action":"stop"},{"id":153,"athleteId":0,"art":"liegend","date":"2021-06-27T15:16:14.183Z","action":"start"},{"id":154,"athleteId":0,"date":"2021-06-27T15:16:28.253Z","action":"stop"},{"id":155,"athleteId":0,"art":"liegend","date":"2021-06-27T15:17:22.584Z","action":"start"},{"id":156,"athleteId":0,"date":"2021-06-27T15:17:43.126Z","action":"stop"},{"id":157,"athleteId":0,"art":"liegend","date":"2021-06-27T15:19:39.398Z","action":"start"},{"id":158,"athleteId":0,"art":"liegend","date":"2021-06-27T15:19:42.304Z","action":"start"},{"id":159,"athleteId":0,"date":"2021-06-27T15:20:57.832Z","action":"stop"},{"id":160,"athleteId":0,"art":"liegend","date":"2021-06-27T15:21:27.280Z","action":"start"},{"id":161,"athleteId":0,"date":"2021-06-27T15:22:28.409Z","action":"stop"},{"id":162,"athleteId":0,"date":"2021-06-27T15:37:29.459Z","action":"start"},{"id":163,"athleteId":9,"date":"2021-06-27T15:37:56.485Z","action":"start"},{"id":164,"athleteId":0,"date":"2021-06-27T15:38:30.345Z","action":"stop"},{"id":165,"athleteId":9,"date":"2021-06-27T15:38:47.581Z","action":"start"},{"id":166,"athleteId":9,"date":"2021-06-27T15:39:48.330Z","action":"stop"},{"id":167,"athleteId":0,"date":"2021-06-27T15:39:59.775Z","action":"start"},{"id":168,"athleteId":0,"date":"2021-06-27T15:41:00.438Z","action":"stop"},{"id":169,"athleteId":0,"date":"2021-06-27T15:41:06.841Z","action":"start"},{"id":170,"athleteId":0,"date":"2021-06-27T15:41:17.838Z","action":"stop"},{"id":171,"athleteId":0,"date":"2021-06-27T15:41:24.739Z","action":"start"},{"id":172,"athleteId":0,"date":"2021-06-27T15:41:31.767Z","action":"stop"},{"id":173,"athleteId":0,"date":"2021-06-27T15:41:45.450Z","action":"start"},{"id":174,"athleteId":0,"date":"2021-06-27T15:41:47.249Z","action":"start"},{"id":175,"athleteId":0,"date":"2021-06-27T15:42:04.840Z","action":"stop"},{"id":176,"athleteId":0,"date":"2021-06-27T15:42:10.402Z","action":"start"},{"id":177,"athleteId":0,"date":"2021-06-27T15:42:21.635Z","action":"stop"},{"id":178,"athleteId":0,"date":"2021-06-27T15:42:30.891Z","action":"start"},{"id":179,"athleteId":0,"date":"2021-06-27T15:43:08.637Z","action":"stop"},{"id":180,"athleteId":0,"date":"2021-06-27T15:43:18.852Z","action":"start"},{"id":181,"athleteId":0,"date":"2021-06-27T15:43:27.997Z","action":"stop"},{"id":182,"athleteId":0,"date":"2021-06-27T15:43:51.156Z","action":"start"},{"id":183,"athleteId":0,"date":"2021-06-27T15:44:03.046Z","action":"stop"},{"id":184,"athleteId":0,"date":"2021-06-27T15:44:08.605Z","action":"start"},{"id":185,"athleteId":0,"date":"2021-06-27T15:44:15.105Z","action":"stop"},{"id":186,"athleteId":0,"date":"2021-06-27T15:45:04.737Z","action":"start"},{"id":187,"athleteId":0,"date":"2021-06-27T15:46:05.596Z","action":"stop"},{"id":188,"athleteId":0,"date":"2021-06-27T15:48:08.531Z","action":"start"},{"id":189,"athleteId":0,"date":"2021-06-27T15:49:09.911Z","action":"stop"},{"id":190,"athleteId":0,"date":"2021-06-27T15:50:04.844Z","action":"start"},{"id":191,"athleteId":0,"date":"2021-06-27T15:50:27.211Z","action":"stop"},{"id":192,"athleteId":0,"date":"2021-06-27T16:02:29.920Z","action":"start"},{"id":193,"athleteId":0,"date":"2021-06-27T16:02:51.569Z","action":"stop"},{"id":194,"athleteId":0,"date":"2021-06-27T16:07:26.382Z","action":"start"},{"id":195,"athleteId":0,"date":"2021-06-27T16:07:56.095Z","action":"stop"},{"id":196,"athleteId":0,"art":"liegend","date":"2021-06-27T16:11:15.735Z","action":"start"},{"id":197,"athleteId":0,"date":"2021-06-27T16:12:16.221Z","action":"stop"},{"id":198,"athleteId":9,"date":"2021-06-27T16:12:34.062Z","action":"start"},{"id":199,"athleteId":9,"date":"2021-06-27T16:12:53.049Z","action":"stop"},{"id":200,"athleteId":0,"art":"liegend","date":"2021-06-27T16:15:31.349Z","action":"start"},{"id":201,"athleteId":0,"date":"2021-06-27T16:15:52.243Z","action":"stop"},{"id":202,"athleteId":0,"art":"liegend","date":"2021-06-27T16:15:56.618Z","action":"start"},{"id":203,"athleteId":0,"art":"liegend","date":"2021-06-27T16:16:17.174Z","action":"start"},{"id":204,"athleteId":0,"date":"2021-06-27T16:16:27.468Z","action":"stop"},{"id":205,"athleteId":0,"art":"liegend","date":"2021-06-27T16:16:32.774Z","action":"start"},{"id":206,"athleteId":0,"date":"2021-06-27T16:16:52.569Z","action":"stop"},{"id":207,"athleteId":0,"art":"liegend","date":"2021-06-27T16:18:04.427Z","action":"start"},{"id":208,"athleteId":0,"date":"2021-06-27T16:18:14.178Z","action":"stop"},{"id":209,"athleteId":9,"date":"2021-06-27T16:20:15.384Z","action":"start"},{"id":210,"athleteId":9,"date":"2021-06-27T16:20:37.738Z","action":"stop"},{"id":211,"athleteId":9,"date":"2021-06-27T16:22:17.284Z","action":"start"},{"id":212,"athleteId":9,"date":"2021-06-27T16:22:35.301Z","action":"stop"},{"id":213,"athleteId":9,"date":"2021-06-27T16:28:49.832Z","action":"start"},{"id":214,"athleteId":9,"date":"2021-06-27T16:29:41.071Z","action":"stop"},{"id":215,"athleteId":9,"date":"2021-06-27T16:30:52.001Z","action":"start"},{"id":216,"athleteId":9,"date":"2021-06-27T16:31:21.435Z","action":"stop"},{"id":217,"athleteId":9,"date":"2021-06-27T16:31:36.787Z","action":"start"},{"id":218,"athleteId":9,"date":"2021-06-27T16:31:58.865Z","action":"start"},{"id":219,"athleteId":9,"date":"2021-06-27T16:32:37.207Z","action":"stop"}]